prezzibenzina/__init__.py
prezzibenzina_py-1.1.4.dist-info/METADATA
prezzibenzina_py-1.1.4.dist-info/RECORD
prezzibenzina_py-1.1.4.dist-info/WHEEL
prezzibenzina_py-1.1.4.dist-info/top_level.txt
