Metadata-Version: 2.1
Name: prezzibenzina-py
Version: 1.1.4
Summary: A python package to get Prezzibenzina info
Home-page: https://github.com/eliseomartelli/prezzibenzina_py
Author: Eliseo Martelli
Author-email: me@eliseomartelli.it
License: mit
Platform: any
Classifier: Programming Language :: Python :: 3
Classifier: License :: OSI Approved :: MIT License
Classifier: Operating System :: OS Independent
Provides-Extra: testing
Requires-Dist: requests (>=2.0)
Requires-Dist: beautifulsoup4
Provides-Extra: testing
Requires-Dist: pytest; extra == 'testing'
Requires-Dist: pytest-cov; extra == 'testing'
